eti_domo/__init__.py
eti_domo-1.0.0.dist-info/LICENSE
eti_domo-1.0.0.dist-info/METADATA
eti_domo-1.0.0.dist-info/WHEEL
eti_domo-1.0.0.dist-info/top_level.txt
eti_domo-1.0.0.dist-info/RECORD
