Metadata-Version: 2.1
Name: eti-domo
Version: 1.0.0
Summary: An interface to the REST API of a Came Eti/Domo server
Home-page: https://github.com/andrea-michielan/eti_domo
Author: Andrea Michielan
Author-email: michielan8@gmail.com
License: UNKNOWN
Platform: UNKNOWN
Classifier: Programming Language :: Python :: 3
Classifier: License :: OSI Approved :: MIT License
Classifier: Operating System :: OS Independent
Requires-Python: >=3.6
Requires-Dist: requests
